{
  "id": "chunk_2_209",
  "chuong": "chương 2. hành vi vi phạm, hình thức, mức xử phạt, mức trừ điểm giấy phép lái xe và biện pháp khắc phục hậu quả vi phạm hành chính về trật tự, an toàn giao thông trong lĩnh vực giao thông đường bộ",
  "muc": "mục 5. các vi phạm khác liên quan đến trật tự, an toàn giao thông trong lĩnh vực giao thông đường bộ",
  "dieu": "điều 33. xử phạt hành khách đi xe vi phạm quy định về trật tự, an toàn giao thông",
  "khoan": "khoản 1. phạt tiền từ 100.000 đồng đến 200.000 đồng đối với một trong các hành vi vi phạm sau đây:",
  "content": "khoản 1. phạt tiền từ 100.000 đồng đến 200.000 đồng đối với một trong các hành vi vi phạm sau đây:\na) không chấp hành hướng dẫn của lái xe, nhân viên phục vụ trên xe về các quy định bảo đảm trật tự, an toàn giao thông;\nb) gây mất trật tự trên xe.",
  "reference_id": "2.5.33.1"
}